README.md
setup.py
Binsearch/BinarySearch.py
Binsearch.egg-info/PKG-INFO
Binsearch.egg-info/SOURCES.txt
Binsearch.egg-info/dependency_links.txt
Binsearch.egg-info/not-zip-safe
Binsearch.egg-info/top_level.txt