Metadata-Version: 2.1
Name: Binsearch
Version: 1.0
Summary: Binsearchpy library is created with binary seach algorithm to make the search faster from list data structure
Home-page: UNKNOWN
Author: Dheeraj Kumar
Author-email: engineerdheeraj97@gmail.com
License: MIT
Keywords: python,Binarysearch,algorithm,list,Binary,BinaryList
Platform: UNKNOWN
Classifier: Development Status :: 1 - Planning
Classifier: Intended Audience :: Developers
Classifier: Programming Language :: Python :: 3
Classifier: Operating System :: Unix
Classifier: Operating System :: Microsoft :: Windows
